tenor/__init__.py
tenor/tenor.py
tenor.py-0.0.1.dist-info/METADATA
tenor.py-0.0.1.dist-info/WHEEL
tenor.py-0.0.1.dist-info/top_level.txt
tenor.py-0.0.1.dist-info/RECORD
