Metadata-Version: 2.1
Name: tenor.py
Version: 0.0.1
Summary: Gif 검색 라이브러리
Home-page: https://github.com/cord0318/tenor
Author: Jung Ji-Hyo
Author-email: cord0318@gmail.com
License: GPLv3
Keywords: korea,gif,tenor,움짤,tenor.py
Platform: UNKNOWN
Classifier: Programming Language :: Python :: 3.8
Classifier: License :: OSI Approved :: GNU General Public License v3 (GPLv3)
Classifier: Development Status :: 5 - Production/Stable
Requires-Python: >=3
Requires-Dist: asyncio
Requires-Dist: aiohttp
Requires-Dist: aiofiles
